{"inkVersion":20,"root":[[{"->":"BEGINNING"},["done",{"#f":5,"#n":"g-0"}],null],"done",{"BEGINNING":[{"#":"name Detective G"},"^Yo, C. Boss fill you in on the deets?","\n",{"#":"name player"},"^Yes, he did.","\n","^How on Terra-2 did you lose your Neuralyzer?","\n","^That's awfully careless of you, G.","\n",{"#":"name Detective G."},"^Hey, I am like 50 percent certain it was stolen.","\n","^And because I have two heads, that makes me 100% sure.","\n",{"#":"name player"},"^You sure you didn't just misplace your memmory gun?","\n",{"#":"name Detective G"},"^Positive-o-lutely!","\n","^I got a perfect memory, remember?","\n","^At least, the other head does.","\n",{"#":"name player"},"^So, what do you remember?","\n",{"#":"name Detective G"},"^I went into the evidence room three relative days ago, solving cases mad fast, the usual.","\n","^I was all alone, and nothing happened.","\n","^But when I left the room, my memory gun was looong gone.","\n",{"#":"name player"},"^Well, either you misplaced it, or the culprit wiped you.","\n",{"#":"name Detective G"},"^Yup. Sucks being on the recieving end of that thing, that's for sure.","\n",{"#":"name player"},"^And since your memory is wiped, so you're compromised.","\n",{"#":"name Detective G"},"^Ayup. They can't let the GOAT do all the work around here,","\n","^they gotta let some of the other detectives get something done.","\n",{"#":"name player"},"^You're insufferable. I may come back later with more questions.","\n",{"#":"name Detective G"},"^Yeah, you'll need the help.","\n","end",{"#f":1}],"DONE":[{"#":"name Detective G"},"^Yo, you really need help that fast.","\n","^You kinda stoopid!","\n",{"#":"name player"},"^Shut up. I'm investigating.","\n","end",{"#f":1}],"#f":1}],"listDefs":{}}